CHANGES.txt
LICENSE.txt
MANIFEST.in
README.txt
setup.cfg
setup.py
DeCiDa.egg-info/PKG-INFO
DeCiDa.egg-info/SOURCES.txt
DeCiDa.egg-info/dependency_links.txt
DeCiDa.egg-info/not-zip-safe
DeCiDa.egg-info/top_level.txt
bin/calc
bin/dataview
bin/gifimg
bin/ngsp
bin/op
bin/pll_phase_noise
bin/pllss
bin/plotter
bin/simvision_csv2col
bin/twin
decida/Balloonhelp.py
decida/BinarySearch.py
decida/Calc.py
decida/CanvasIdentify.py
decida/Contourx.py
decida/Data.py
decida/DataViewm.py
decida/DialogBase.py
decida/EquationParser.py
decida/Fitter.py
decida/FormulaCalculator.py
decida/FrameNotebook.py
decida/GetEntryDialog.py
decida/Histogramx.py
decida/ItclObjectx.py
decida/Itemizer.py
decida/LevMar.py
decida/MessageDialog.py
decida/NGspice.py
decida/PLL.py
decida/PLLphaseNoise.py
decida/Parameter.py
decida/Parameters.py
decida/Pattern.py
decida/PlotBasem.py
decida/Plotterm.py
decida/Report.py
decida/SelectionDialog.py
decida/SimulatorNetlist.py
decida/SmithChartx.py
decida/StatusDialog.py
decida/Tckt.py
decida/TextWindow.py
decida/XYplotm.py
decida/__init__.py
decida/baseconvert.py
decida/entry_emacs_bindings.py
decida/grep.py
decida/interpolate.py
decida/multiline.py
decida/pattern_alignment.py
decida/range_sample.py
decida/readfile2list.py
decida/spice_value.py
decida/syscall.py
decida/vtb.py
decida/writelist2file.py
decida/dataview_help/Annotation
decida/dataview_help/DataRemoval
decida/dataview_help/DataviewMenus
decida/dataview_help/EquationSet
decida/dataview_help/KeyBindings
decida/dataview_help/LineParameter
decida/dataview_help/Mouse
decida/dataview_help/PlotMenus
decida/dataview_help/ScriptExample
decida/dataview_help/TableOfContents
decida/dataview_help/Usage
decida/dataview_help/Zoom
decida/dataview_help/dataview.txt
decida/test/__init__.py
decida/test/test_Balloonhelp.py
decida/test/test_BinarySearch_1.py
decida/test/test_BinarySearch_2.py
decida/test/test_Calc_1.py
decida/test/test_Calc_2.py
decida/test/test_Contourx_1.py
decida/test/test_Contourx_2.py
decida/test/test_DataViewm_1.py
decida/test/test_DataViewm_2.py
decida/test/test_DataViewm_3.py
decida/test/test_DataViewm_4.py
