Metadata-Version: 1.1
Name: DeCiDa
Version: 1.1.5
Summary: Device and Circuit Data Analysis
Home-page: http://decida.org
Author: Richard Booth
Author-email: rvhbooth@gmail.com
License: LICENSE.txt
Platform: Linux
Platform: MacOS
Platform: CygWin
Platform: Windows
Classifier: License :: OSI Approved :: BSD License
Classifier: Operating System :: OS Independent
Classifier: Programming Language :: Python :: 2.7
Classifier: Programming Language :: Python :: 3
Classifier: Topic :: Multimedia :: Graphics
Classifier: Topic :: Scientific/Engineering
Classifier: Topic :: Scientific/Engineering :: Electronic Design Automation (EDA)
Classifier: Topic :: Scientific/Engineering :: Visualization
